{
  "branch": "refactor/391-cleanup-legacy-naming-and-architecture",
  "issue_number": 391,
  "workflow_name": "refactor",
  "current_phase": "implementation",
  "current_cycle": 2,
  "last_cycle": 1,
  "cycle_history": [
    {
      "cycle_number": 2,
      "name": "C_CLEANUP.2",
      "forced": false,
      "entered": "2026-06-10T06:14:28.025321+00:00"
    }
  ],
  "required_phases": [
    "research",
    "planning",
    "implementation",
    "validation",
    "documentation",
    "ready"
  ],
  "execution_mode": "interactive",
  "skip_reason": "Design phase output (decomposition, sequencing, naming decisions, approved strategy) is fully captured in the #289 tracker body. No separate design artifact needed \u2014 all cross-issue contracts are explicit in the tracker. Child issues #285, #384, #385, #386, #387, #388 are created and sequenced.",
  "issue_title": "refactor(mcp-server): Cleanup legacy naming, docs, tests, and archive files",
  "parent_branch": "epic/289-installable-wheel-standalone-mcp-server",
  "created_at": "2026-06-09T20:24:36.669833+00:00",
  "transitions": [
    {
      "from_phase": "research",
      "to_phase": "planning",
      "timestamp": "2026-06-10T05:56:58.188815+00:00",
      "human_approval": null,
      "forced": false,
      "skip_reason": null
    },
    {
      "from_phase": "planning",
      "to_phase": "implementation",
      "timestamp": "2026-06-10T06:13:29.437122+00:00",
      "human_approval": null,
      "forced": false,
      "skip_reason": null
    }
  ],
  "reconstructed": false,
  "current_sub_phase": null
}